zhang2016dependency/__init__.py
zhang2016dependency/model.py
zhang2016dependency-0.1.0.dist-info/LICENSE.md
zhang2016dependency-0.1.0.dist-info/METADATA
zhang2016dependency-0.1.0.dist-info/WHEEL
zhang2016dependency-0.1.0.dist-info/top_level.txt
zhang2016dependency-0.1.0.dist-info/zip-safe
zhang2016dependency-0.1.0.dist-info/RECORD
