Metadata-Version: 2.1
Name: zhang2016dependency
Version: 0.1.0
Summary: Implementation of zhang2016dependency
Home-page: https://github.com/wnohang/zhang2016dependency
Author: Cesar Perez
Author-email: cperez@wnohang.com
License: MIT
Project-URL: Issues, https://github.com/wnohang/zhang2016dependency/issues
Project-URL: Source, https://github.com/wnohang/zhang2016dependency
Keywords: research model
Platform: UNKNOWN
Classifier: Development Status :: 1 - Planning
Classifier: Intended Audience :: Developers
Classifier: Intended Audience :: Science/Research
Classifier: License :: OSI Approved :: MIT License
Classifier: Programming Language :: Python :: 3.6
Classifier: Topic :: Education
Classifier: Topic :: Scientific/Engineering :: Artificial Intelligence
Requires-Dist: keras
